climetlab/__init__.py
climetlab/__main__.py
climetlab/_version.py
climetlab/aaa.py
climetlab/debug.py
climetlab/decorators.py
climetlab/exceptions.py
climetlab/mockup.py
climetlab/normalize.py
climetlab/profiling.py
climetlab/prompt.py
climetlab/testing.py
climetlab/arguments/__init__.py
climetlab/arguments/args_kwargs.py
climetlab/arguments/argument.py
climetlab/arguments/climetlab_types.py
climetlab/arguments/guess.py
climetlab/arguments/input_manager.py
climetlab/arguments/transformers.py
climetlab/config/units.yaml
climetlab/core/__init__.py
climetlab/core/caching.py
climetlab/core/constants.py
climetlab/core/data.py
climetlab/core/index.py
climetlab/core/initialise.py
climetlab/core/ipython.py
climetlab/core/metadata.py
climetlab/core/order.py
climetlab/core/plugins.py
climetlab/core/select.py
climetlab/core/settings.py
climetlab/core/statistics.py
climetlab/core/temporary.py
climetlab/core/thread.py
climetlab/dask/__init__.py
climetlab/data/css/table.css
climetlab/data/dask/local.yaml
climetlab/data/dask/slurm.yaml
climetlab/data/dask/ssh.yaml
climetlab/data/domains/verification.yaml
climetlab/data/layers/default-background.yaml
climetlab/data/layers/default-foreground.yaml
climetlab/data/layers/example-foreground.yaml
climetlab/data/layers/land-sea.yaml
climetlab/data/projections/africa.yaml
climetlab/data/projections/asia.yaml
climetlab/data/projections/bonne.yaml
climetlab/data/projections/collignon.yaml
climetlab/data/projections/euro-atlantic.yaml
climetlab/data/projections/europe-cylindrical.yaml
climetlab/data/projections/europe.yaml
climetlab/data/projections/global.yaml
climetlab/data/projections/goode.yaml
climetlab/data/projections/mercator.yaml
climetlab/data/projections/mollweide.yaml
climetlab/data/projections/north-america.yaml
climetlab/data/projections/north-america1.yaml
climetlab/data/projections/north-atlantic.yaml
climetlab/data/projections/north-hemisphere.yaml
climetlab/data/projections/polar-north.yaml
climetlab-0.24.0.dist-info/LICENSE
climetlab-0.24.0.dist-info/METADATA
climetlab-0.24.0.dist-info/WHEEL
climetlab-0.24.0.dist-info/entry_points.txt
climetlab-0.24.0.dist-info/top_level.txt
climetlab-0.24.0.dist-info/RECORD
