Metadata-Version: 2.1
Name: climetlab
Version: 0.24.0
Summary: Handling of climate/meteorological dataa.
Author-email: "European Centre for Medium-Range Weather Forecasts (ECMWF)" <software.support@ecmwf.int>
License: Apache License
Project-URL: Homepage, https://github.com/ecmwf/climetlab/
Project-URL: Documentation, https://climetlab.readthedocs.io/
Project-URL: Repository, https://github.com/ecmwf/climetlab/
Project-URL: Issues, https://github.com/ecmwf/climetlab/issues
Keywords: tools,datasets,ai
Classifier: Development Status :: 4 - Beta
Classifier: Intended Audience :: Developers
Classifier: License :: OSI Approved :: Apache Software License
Classifier: Programming Language :: Python :: 3
Classifier: Programming Language :: Python :: 3.9
Classifier: Programming Language :: Python :: 3.10
Classifier: Programming Language :: Python :: 3.11
Classifier: Programming Language :: Python :: Implementation :: CPython
Classifier: Programming Language :: Python :: Implementation :: PyPy
Classifier: Operating System :: OS Independent
Requires-Python: >=3.9
License-File: LICENSE
Requires-Dist: requests
Requires-Dist: branca
Requires-Dist: cdsapi
Requires-Dist: cfgrib >=0.9.10.1
Requires-Dist: dask
Requires-Dist: earthkit-meteo
Requires-Dist: eccodes >=1.3.0
Requires-Dist: ecmwf-api-client >=1.6.1
Requires-Dist: ecmwf-opendata >=0.1.2
Requires-Dist: ecmwflibs >=0.6.3
Requires-Dist: entrypoints
Requires-Dist: filelock
Requires-Dist: imageio
Requires-Dist: lru-dict
Requires-Dist: magics >=1.5.6
Requires-Dist: markdown
Requires-Dist: multiurl >=0.1.0
Requires-Dist: netcdf4
Requires-Dist: numpngw
Requires-Dist: pdbufr
Requires-Dist: pyodc
Requires-Dist: pyyaml
Requires-Dist: termcolor
Requires-Dist: toolz
Requires-Dist: tqdm
Requires-Dist: xarray
Provides-Extra: interactive
Requires-Dist: skinnywms ; extra == 'interactive'
Requires-Dist: folium >=0.12.1 ; extra == 'interactive'
Provides-Extra: tensorflow
Requires-Dist: tensorflow ; extra == 'tensorflow'
Provides-Extra: zarr
Requires-Dist: zarr ; extra == 'zarr'
Requires-Dist: s3fs ; extra == 'zarr'
